traders_copilot_mzza_25/__init__.py
traders_copilot_mzza_25/data.py
traders_copilot_mzza_25/generate_signals.py
traders_copilot_mzza_25/indicators.py
traders_copilot_mzza_25/plot_signals.py
traders_copilot_mzza_25-0.1.1.dist-info/LICENSE
traders_copilot_mzza_25-0.1.1.dist-info/METADATA
traders_copilot_mzza_25-0.1.1.dist-info/WHEEL
traders_copilot_mzza_25-0.1.1.dist-info/RECORD
