Metadata-Version: 2.3
Name: traders_copilot_mzza_25
Version: 0.1.1
Summary: The package is designed to signal traders, and thus helping with streamlining investment decision-making and optimizing trading strategies.
License: MIT
Author: Mingyang Zhang, Zanan Pech, Ziyuan Zhao and Abeba Nigussie Turi
Requires-Python: >=3.11
Classifier: License :: OSI Approved :: MIT License
Classifier: Programming Language :: Python :: 3
Classifier: Programming Language :: Python :: 3.11
Classifier: Programming Language :: Python :: 3.12
Classifier: Programming Language :: Python :: 3.13
Requires-Dist: matplotlib (>=3.10.0)
Requires-Dist: myst_nb (>=0.18.0)
Requires-Dist: numpy (>=2.2.1)
Requires-Dist: pandas (>=2.2.3)
Requires-Dist: pytest (>=8.3.4)
Requires-Dist: sphinx (>=7.0.0)
Requires-Dist: sphinx-autoapi (>=2.0.0)
Requires-Dist: sphinx_rtd_theme (>=1.2.0)
